LICENSE
pybetter/__init__.py
pybetter/__main__.py
pybetter/cli.py
pybetter/improvements.py
pybetter/transformers/__init__.py
pybetter/transformers/all_attribute.py
pybetter/transformers/base.py
pybetter/transformers/boolean_equality.py
pybetter/transformers/empty_fstring.py
pybetter/transformers/equals_none.py
pybetter/transformers/mutable_args.py
pybetter/transformers/nested_withs.py
pybetter/transformers/not_in.py
pybetter/transformers/not_is.py
pybetter/transformers/parenthesized_return.py
pybetter/transformers/unhashable_list.py
pybetter/utils.py
pybetter-0.4.0.dist-info/entry_points.txt
pybetter-0.4.0.dist-info/LICENSE
pybetter-0.4.0.dist-info/WHEEL
pybetter-0.4.0.dist-info/METADATA
pybetter-0.4.0.dist-info/RECORD
