Metadata-Version: 2.1
Name: pybetter
Version: 0.4.0
Summary: Tool for fixing trivial problems with your code.
Home-page: https://github.com/lensvol/pybetter
License: MIT
Keywords: ast
Author: Kirill Borisov
Author-email: lensvol@gmail.com
Requires-Python: >=3.6,<4.0
Classifier: Development Status :: 3 - Alpha
Classifier: Environment :: Console
Classifier: Intended Audience :: Developers
Classifier: License :: OSI Approved :: MIT License
Classifier: Operating System :: OS Independent
Classifier: Programming Language :: Python
Classifier: Programming Language :: Python :: 3
Classifier: Programming Language :: Python :: 3.6
Classifier: Programming Language :: Python :: 3.7
Classifier: Programming Language :: Python :: 3.8
Classifier: Programming Language :: Python :: 3.9
Classifier: Topic :: Software Development
Classifier: Topic :: Software Development :: Quality Assurance
Classifier: Topic :: Utilities
Requires-Dist: click (>=7.0,<8.0)
Requires-Dist: hypothesmith (>=0.1.8,<0.2.0)
Requires-Dist: libcst (>=0.3.16,<0.4.0)
Requires-Dist: pyemojify (>=0.2.0,<0.3.0)
Requires-Dist: pygments (>=2.5.2,<3.0.0)
Project-URL: Repository, https://github.com/lensvol/pybetter
